feeds/__init__.py
feeds/display.py
feeds/input_mod.py
feeds/main.py
feeds/utils.py
2feeds-1.0.210.dist-info/METADATA
2feeds-1.0.210.dist-info/WHEEL
2feeds-1.0.210.dist-info/entry_points.txt
2feeds-1.0.210.dist-info/top_level.txt
2feeds-1.0.210.dist-info/RECORD
