Metadata-Version: 2.1
Name: 2feeds
Version: 1.0.210
Summary: A cli to read feeds
Home-page: UNKNOWN
Author: asif
Author-email: 
License: UNKNOWN
Project-URL: Source Code, https://github.com/asif42/feed-reader
Keywords: rss cli urwid
Platform: UNKNOWN
Classifier: Development Status :: 3 - Alpha
Classifier: Topic :: Utilities
Classifier: License :: OSI Approved :: BSD License
Requires-Python: >=3.7.4
Requires-Dist: feedparser (==5.2.1)
Requires-Dist: urwid (==2.0.1)
